<?xml version="1.0" encoding="utf-8"?>
<LanguageData>
  <!--The following translations were generated by https://www.deepl.com/-->
  <WarehouseLabel>Склад</WarehouseLabel>
  <TraderWarehouseTitle>Оплатить стоимость доставки</TraderWarehouseTitle>
  <TraderWarehouseTitleTip>Оплатите стоимость доставки для текущей операции.
Размер платы за доставку зависит от веса товара, который вы будете передавать.

Обратите внимание, что RimBank™ оставит сдачу себе, а не вернет ее вам. Подумайте дважды, прежде чем совершать переплату.</TraderWarehouseTitleTip>
  <WarehouseSilverTip>Количество серебра, подлежащего оплате.</WarehouseSilverTip>
  <VaultLabel>Хранилище</VaultLabel>
  <TraderVaultTitleTip>Храните свои деньги здесь, в безопасности.

Никаких дополнительных сборов за валюту в вашем хранилище, но в сумме это не должно превышать вместимость ($ {0}).</TraderVaultTitleTip>
  <VaultSilverTip>Серебро на земле или в хранилище.</VaultSilverTip>
  <VaultBankNoteTip>Банкноты на земле или в хранилище.</VaultBankNoteTip>
  <MsgExceedsVaultCapacity>Операция не удалась: валюта превысит емкость хранилища ($ {0}).</MsgExceedsVaultCapacity>
  <StaticChamberLabel>Статическая камера</StaticChamberLabel>
  <TraderStaticChamberTitle>Оплатить аренду</TraderStaticChamberTitle>
  <TraderStaticChamberTitleTip>Платите за аренду. $ {0} за человека
Стоимость отзыва статической камеры включена в стоимость аренды, поэтому никаких дополнительных платежей не будет.

Обратите внимание, что RimBank™ оставит сдачу себе, вместо того чтобы вернуть ее вам. Подумайте дважды, прежде чем переплачивать.</TraderStaticChamberTitleTip>
  <GlobalDropPodLabel>Global DropPod</GlobalDropPodLabel>
  <GlobalDropPodCaption>Предметы для доставки</GlobalDropPodCaption>
  <TraderCapManTitle>Оплатить абонентскую плату</TraderCapManTitle>
  <TraderCapManTitleTip>Платите абонентскую плату за все новые расширения. $ {0} за слот.
До начала очередного Цикла арендная плата за расширения не взимается, но абонентская плата не возвращается.

Обратите внимание, что RimBank™ оставит сдачу себе, вместо того чтобы вернуть ее вам. Подумайте дважды, прежде чем совершать переплату.</TraderCapManTitleTip>
  <TraderPayBillTitle>Оплатить просроченные счета</TraderPayBillTitle>
  <TraderPayBillTitleTip>Очистите просроченные счета, чтобы снять ограничения на услуги.

Обратите внимание, что RimBank™ оставит сдачу себе, а не вернет ее вам. Подумайте дважды, прежде чем переплачивать.</TraderPayBillTitleTip>
</LanguageData>